orbis_plugin_aggregation_dbpedia_entity_types/__init__.py
orbis_plugin_aggregation_dbpedia_entity_types/main.py
orbis_plugin_aggregation_dbpedia_entity_types/regex_patterns.py
orbis_plugin_aggregation_dbpedia_entity_types-2.2.4.dist-info/LICENSE
orbis_plugin_aggregation_dbpedia_entity_types-2.2.4.dist-info/METADATA
orbis_plugin_aggregation_dbpedia_entity_types-2.2.4.dist-info/WHEEL
orbis_plugin_aggregation_dbpedia_entity_types-2.2.4.dist-info/top_level.txt
orbis_plugin_aggregation_dbpedia_entity_types-2.2.4.dist-info/RECORD
