Metadata-Version: 2.1
Name: orbis-plugin-aggregation-dbpedia-entity-types
Version: 2.2.4
Summary: The dbpedia_entity_types aggregation plugin for Orbis
Home-page: https://github.com/orbis-eval/orbis_plugin_aggregation_dbpedia_entity_types
Author: fabod
License: GPL2
Platform: UNKNOWN
Requires-Python: >3.6
Requires-Dist: SPARQLWrapper (==1.8.2)
Requires-Dist: regex (==2018.2.21)
